tests/__init__.py
tests/test_client.py
whisper_live/__init__.py
whisper_live/__version__.py
whisper_live/client.py
whisper_live/transcription_client.py
whisper_live/transcription_tee_client.py
whisper_live/utils.py
whisper_live_client-0.6.3.dist-info/licenses/LICENSE
whisper_live_client-0.6.3.dist-info/METADATA
whisper_live_client-0.6.3.dist-info/WHEEL
whisper_live_client-0.6.3.dist-info/top_level.txt
whisper_live_client-0.6.3.dist-info/RECORD
