Metadata-Version: 2.4
Name: whisper_live_client
Version: 0.6.3
Summary: Lightweight Python client for WhisperLive — fewer dependencies, optimized for client-only use and easy integration.
Home-page: https://github.com/B4dT0bi/WhisperLiveClient
Author: Tobias Boese
Author-email: tobias.boese@gmail.com
License: MIT
Classifier: Development Status :: 4 - Beta
Classifier: Intended Audience :: Developers
Classifier: Intended Audience :: Science/Research
Classifier: License :: OSI Approved :: MIT License
Classifier: Programming Language :: Python :: 3
Classifier: Programming Language :: Python :: 3 :: Only
Classifier: Programming Language :: Python :: 3.8
Classifier: Programming Language :: Python :: 3.9
Classifier: Topic :: Scientific/Engineering :: Artificial Intelligence
Requires-Python: >=3.8
License-File: LICENSE
Requires-Dist: PyAudio
Requires-Dist: av
Requires-Dist: scipy
Requires-Dist: websocket-client
Dynamic: author
Dynamic: author-email
Dynamic: classifier
Dynamic: description
Dynamic: description-content-type
Dynamic: home-page
Dynamic: license
Dynamic: license-file
Dynamic: requires-dist
Dynamic: requires-python
Dynamic: summary
